{
    "set1":[
        "Суши",
        "Вкусные и свежие",
        "images/2.1.jpg"

    ],
    "set2":[
        "Суши",
        "Вкусные и свежие",
        "images/2.1.jpg"

    ],
    "set3":[
        "Суши",
        "Вкусные и свежие",
        "images/2.1.jpg"

    ],
    "set4":[
        "Суши",
        "Вкусные и свежие",
        "images/2.1.jpg"

    ],
    "set5":[
        "Суши",
        "Вкусные и свежие",
        "images/2.1.jpg"

    ],
    "set6":[
        "Суши",
        "Вкусные и свежие",
        "images/2.1.jpg"

    ],
    "set7":[
        "Суши",
        "Вкусные и свежие",
        "images/2.1.jpg"

    ],
    "set8":[
        "Суши",
        "Вкусные и свежие",
        "images/2.1.jpg"

    ],
    "set9":[
        "Суши",
        "Вкусные и свежие",
        "images/2.1.jpg"

    ],
    "set10":[
        "Суши",
        "Вкусные и свежие",
        "images/2.1.jpg"

    ]
}